australian_ntv2_grid_conversion/__init__.py
australian_ntv2_grid_conversion/australian_ntv2_grid_conversion.py
australian_ntv2_grid_conversion/data/A66 National (13.09.01).gsb
australian_ntv2_grid_conversion/data/National 84 (02.07.01).gsb
australian_ntv2_grid_conversion-1.1.5.dist-info/DESCRIPTION.rst
australian_ntv2_grid_conversion-1.1.5.dist-info/METADATA
australian_ntv2_grid_conversion-1.1.5.dist-info/RECORD
australian_ntv2_grid_conversion-1.1.5.dist-info/WHEEL
australian_ntv2_grid_conversion-1.1.5.dist-info/entry_points.txt
australian_ntv2_grid_conversion-1.1.5.dist-info/metadata.json
australian_ntv2_grid_conversion-1.1.5.dist-info/top_level.txt
