Metadata-Version: 2.0
Name: australian-ntv2-grid-conversion
Version: 1.1.5
Summary: Converts between Australian coordinate systems AGD66/AGD84 and GDA94 using ntv2 grid files
Home-page: http://plaintech.net.au/australian_ntv2_grid_conversion
Author: PHil Howarth
Author-email: phil@plaintech.net.au
License: GPLv3+
Keywords: conversion,AGD,AGD66,AGD84,GDA,GDA94,latitude,longitude
Platform: UNKNOWN
Classifier: Programming Language :: Python
Classifier: Programming Language :: Python :: 3
Classifier: Programming Language :: Python :: 2
Classifier: Development Status :: 4 - Beta
Classifier: Environment :: Other Environment
Classifier: Intended Audience :: Developers
Classifier: Intended Audience :: Science/Research
Classifier: License :: OSI Approved :: GNU General Public License v3 or later (GPLv3+)
Classifier: Natural Language :: English
Classifier: Operating System :: OS Independent
Classifier: Topic :: Software Development :: Libraries :: Python Modules
Classifier: Topic :: Scientific/Engineering :: GIS
Requires-Dist: redfearn
